bhqui-4.2.2.dist-info/licenses/LICENSE
bhqui4/LICENSE
bhqui4/__init__.py
bhqui4/_developer_extras.py
bhqui4/_icons_cache.py
bhqui4/_preset.py
bhqui4/_progress.py
bhqui4/_unique_name.py
bhqui4/_wrapped_text.py
bhqui-4.2.2.dist-info/METADATA
bhqui-4.2.2.dist-info/WHEEL
bhqui-4.2.2.dist-info/top_level.txt
bhqui-4.2.2.dist-info/RECORD
