Metadata-Version: 2.4
Name: bhqui
Version: 4.2.2
Summary: UI components for Blender extensions
Author-email: Ivan Perevala <ivan95perevala@gmail.com>
License-Expression: GPL-3.0-or-later
Project-URL: Homepage, https://github.com/ivan-perevala/lib_bhqui
Project-URL: Issues, https://github.com/ivan-perevala/lib_bhqui/issues
Project-URL: Documentation, https://lib-bhqui.readthedocs.io/4.2.2/
Keywords: bpy,ui
Classifier: Programming Language :: Python :: 3
Classifier: Operating System :: OS Independent
Classifier: Development Status :: 5 - Production/Stable
Requires-Python: >=3.11
License-File: LICENSE
Provides-Extra: docs
Requires-Dist: sphinx; extra == "docs"
Requires-Dist: sphinx-intl; extra == "docs"
Requires-Dist: furo; extra == "docs"
Provides-Extra: tests
Requires-Dist: pytest; extra == "tests"
Requires-Dist: codespell; extra == "tests"
Dynamic: license-file
